{
  "db_name": "PostgreSQL",
  "query": "\n            WITH insert_project AS (\n                INSERT INTO project (project_id, project_name)\n                VALUES ('e78398f7-c481-4fd0-b3c4-23a20bdb9648', 'My Project')\n                RETURNING project_id\n            ),\n            insert_warehouse AS (\n                INSERT INTO warehouse (warehouse_name, project_id, status, \"tabular_delete_mode\")\n                SELECT 'My Warehouse', project_id, 'active', 'hard'\n                FROM insert_project\n                RETURNING warehouse_id\n            )\n            INSERT INTO task_log (\n                task_id,\n                attempt,\n                warehouse_id,\n                queue_name,\n                task_data,\n                status,\n                entity_id,\n                entity_name,\n                entity_type,\n                project_id,\n                attempt_scheduled_for,\n                task_created_at,\n                created_at\n            )\n            VALUES\n            (\n                '550e8400-e29b-41d4-a716-446655440001'::uuid,\n                1,\n                (SELECT warehouse_id FROM insert_warehouse),\n                'metadata_sync',\n                '{\"table_id\": \"customers\"}'::jsonb,\n                'success'::task_final_status,\n                '550e8400-e29b-41d4-a716-446655440101'::uuid,\n                ARRAY['customers']::text[],\n                'table'::entity_type,\n                'e78398f7-c481-4fd0-b3c4-23a20bdb9648'::uuid,\n                now() - make_interval(days => ($1 + 5)::int),\n                now() - make_interval(days => ($1 + 5)::int),\n                now() - make_interval(days => ($1 + 5)::int)\n            ),\n            (\n                '550e8400-e29b-41d4-a716-446655440002'::uuid,\n                1,\n                (SELECT warehouse_id FROM insert_warehouse),\n                'garbage_collection',\n                '{\"schema\": \"prod_analytics\"}'::jsonb,\n                'success'::task_final_status,\n                NULL::uuid,\n                NULL::text[],\n                'warehouse'::entity_type,\n                'e78398f7-c481-4fd0-b3c4-23a20bdb9648'::uuid,\n                now() - make_interval(days => ($1 + 30)::int),\n                now() - make_interval(days => ($1 + 30)::int),\n                now() - make_interval(days => ($1 + 30)::int)\n            ),\n            (\n                $2,\n                1,\n                (SELECT warehouse_id FROM insert_warehouse),\n                'schema_evolution',\n                '{\"column_name\": \"new_discount_column\"}'::jsonb,\n                'success'::task_final_status,\n                '550e8400-e29b-41d4-a716-446655440103'::uuid,\n                ARRAY['orders']::text[],\n                'table'::entity_type,\n                'e78398f7-c481-4fd0-b3c4-23a20bdb9648'::uuid,\n                now() - make_interval(days => ($1 - 60)::int),\n                now() - make_interval(days => ($1 - 60)::int),\n                now() - make_interval(days => ($1 - 60)::int)\n            ),\n            (\n                $3,\n                1,\n                (SELECT warehouse_id FROM insert_warehouse),\n                'file_compaction',\n                '{\"path\": \"/warehouse/parquet\"}'::jsonb,\n                'failed'::task_final_status,\n                NULL::uuid,\n                NULL::text[],\n                'warehouse'::entity_type,\n                'e78398f7-c481-4fd0-b3c4-23a20bdb9648'::uuid,\n                now() - make_interval(days => ($1 - 83)::int),\n                now() - make_interval(days => ($1 - 83)::int),\n                now() - make_interval(days => ($1 - 83)::int)\n            )\n            ",
  "describe": {
    "columns": [],
    "parameters": {
      "Left": [
        "Int4",
        "Uuid",
        "Uuid"
      ]
    },
    "nullable": []
  },
  "hash": "70daf8c784c4ae5c11b2608f7da958508b0a26f4e671a29632fbcbfc55079afc"
}
